{"_type":"export","__export_format":4,"__export_date":"2020-02-04T22:15:36.262Z","__export_source":"insomnia.desktop.app:v7.0.6","resources":[{"_id":"req_9c10c5ecefee4cfc98fcfd7cb5bf2b13","authentication":{},"body":{},"created":1580854198797,"description":"","headers":[],"isPrivate":false,"metaSortKey":-1580854198797,"method":"GET","modified":1580854207965,"name":"View topic","parameters":[],"parentId":"wrk_5f81078700b94aa38694c038ace28c54","settingDisableRenderRequestBody":false,"settingEncodeUrl":true,"settingFollowRedirects":"global","settingRebuildPath":true,"settingSendCookies":true,"settingStoreCookies":true,"url":"{{ base_url  }}/topics/2/view","_type":"request"},{"_id":"wrk_5f81078700b94aa38694c038ace28c54","created":1580737513372,"description":"","modified":1580737513371,"name":"Conhecendo as ISTs","parentId":null,"_type":"workspace"},{"_id":"req_108474cf99214798a1c5608d8c2b5fbb","authentication":{},"body":{"mimeType":"multipart/form-data","params":[{"description":"","id":"pair_b5b8901576f34819992a31edcdf64111","name":"description","value":"Imgem 1"},{"description":"","id":"pair_d46ff58bd0d849b88fa52f1af64b561c","name":"reference","value":"referencia 1"},{"description":"","disabled":true,"id":"pair_5fd43b9cd10d4ec68393d09f167542f9","name":"","value":""},{"description":"","fileName":"/Users/manogel/Documents/ModelagemGeral.png","id":"pair_53b5a027f81f4a3daf5a34c6f1ac2ed9","name":"file","type":"file","value":""}]},"created":1580847884443,"description":"","headers":[{"id":"pair_3ac76a6cfe584728a1ed8d7a880d6d26","name":"Content-Type","value":"multipart/form-data"}],"isPrivate":false,"metaSortKey":-1580794555701,"method":"POST","modified":1580847984207,"name":"add","parameters":[],"parentId":"fld_8ebae47530be4711845a050d46d3ae1c","settingDisableRenderRequestBody":false,"settingEncodeUrl":true,"settingFollowRedirects":"global","settingRebuildPath":true,"settingSendCookies":true,"settingStoreCookies":true,"url":"{{ base_url  }}/topics/2/files","_type":"request"},{"_id":"fld_8ebae47530be4711845a050d46d3ae1c","created":1580847781949,"description":"","environment":{},"environmentPropertyOrder":null,"metaSortKey":-1580847781949,"modified":1580847781949,"name":"UC files in topics","parentId":"wrk_5f81078700b94aa38694c038ace28c54","_type":"request_group"},{"_id":"req_8022c19a5ac7436c91c6aa20898b91b8","authentication":{},"body":{"mimeType":"application/json","text":"{\n\t\"email\": \"manoel@mail.com\",\n\t\"password\": \"123456\"\n}"},"created":1580741338302,"description":"","headers":[{"id":"pair_ba028c6e6408410793f72b4ae8cd7341","name":"Content-Type","value":"application/json"}],"isPrivate":false,"metaSortKey":-1580741338302,"method":"POST","modified":1580741387072,"name":"store","parameters":[],"parentId":"fld_679b4399146a4aadab5cc88a3c15a2d0","settingDisableRenderRequestBody":false,"settingEncodeUrl":true,"settingFollowRedirects":"global","settingRebuildPath":true,"settingSendCookies":true,"settingStoreCookies":true,"url":"{{ base_url  }}/{{ path  }}","_type":"request"},{"_id":"fld_679b4399146a4aadab5cc88a3c15a2d0","created":1580741329453,"description":"","environment":{"path":"sessions"},"environmentPropertyOrder":{"&":["path"]},"metaSortKey":-1580741329453,"modified":1580741351363,"name":"Sessions","parentId":"wrk_5f81078700b94aa38694c038ace28c54","_type":"request_group"},{"_id":"req_a5fdf386eb5d4867a1339e35aae6a23d","authentication":{},"body":{},"created":1580740859062,"description":"","headers":[],"isPrivate":false,"metaSortKey":-1580740859062,"method":"DELETE","modified":1580741446972,"name":"delete","parameters":[],"parentId":"fld_52529351e645428093616206b912bfba","settingDisableRenderRequestBody":false,"settingEncodeUrl":true,"settingFollowRedirects":"global","settingRebuildPath":true,"settingSendCookies":true,"settingStoreCookies":true,"url":"{{ base_url  }}/{{ path  }}/2","_type":"request"},{"_id":"fld_52529351e645428093616206b912bfba","created":1580737638054,"description":"","environment":{"path":"administrators"},"environmentPropertyOrder":{"&":["path"]},"metaSortKey":-1580737638054,"modified":1580737756137,"name":"Administradores","parentId":"wrk_5f81078700b94aa38694c038ace28c54","_type":"request_group"},{"_id":"req_2616f484b94041a980750137828e7e6e","authentication":{},"body":{"mimeType":"application/json","text":"{\n\t\"username\": \"manoel gomes borges\"\n}"},"created":1580739844572,"description":"","headers":[{"id":"pair_ad5ee60f014b4dc6af8bd80b4f65d012","name":"Content-Type","value":"application/json"}],"isPrivate":false,"metaSortKey":-1580739844572,"method":"PUT","modified":1580740471572,"name":"update","parameters":[],"parentId":"fld_52529351e645428093616206b912bfba","settingDisableRenderRequestBody":false,"settingEncodeUrl":true,"settingFollowRedirects":"global","settingRebuildPath":true,"settingSendCookies":true,"settingStoreCookies":true,"url":"{{ base_url  }}/{{ path  }}/1","_type":"request"},{"_id":"req_257186d31d294adda199a47dfba7d8dc","authentication":{},"body":{},"created":1580739456664,"description":"","headers":[],"isPrivate":false,"metaSortKey":-1580739456664,"method":"GET","modified":1580739570634,"name":"index","parameters":[],"parentId":"fld_52529351e645428093616206b912bfba","settingDisableRenderRequestBody":false,"settingEncodeUrl":true,"settingFollowRedirects":"global","settingRebuildPath":true,"settingSendCookies":true,"settingStoreCookies":true,"url":"{{ base_url  }}/{{ path  }}","_type":"request"},{"_id":"req_321f3edf52204bee83f8a2637bcf727a","authentication":{},"body":{"mimeType":"application/json","text":"{\n\t\"username\": \"manoel gomes\",\n\t\"email\": \"Manoel@mail.com\",\n\t\"password\": \"123456\"\n}"},"created":1580737649831,"description":"","headers":[{"id":"pair_3ac76a6cfe584728a1ed8d7a880d6d26","name":"Content-Type","value":"application/json"}],"isPrivate":false,"metaSortKey":-1580737649831,"method":"POST","modified":1580844240366,"name":"store","parameters":[],"parentId":"fld_52529351e645428093616206b912bfba","settingDisableRenderRequestBody":false,"settingEncodeUrl":true,"settingFollowRedirects":"global","settingRebuildPath":true,"settingSendCookies":true,"settingStoreCookies":true,"url":"{{ base_url  }}/{{ path  }}","_type":"request"},{"_id":"req_373d39c96a214eac9f0f385f54b573f9","authentication":{},"body":{},"created":1580844763641,"description":"","headers":[],"isPrivate":false,"metaSortKey":-1580740859062,"method":"DELETE","modified":1580845190066,"name":"delete","parameters":[],"parentId":"fld_a523cf43e0664ea491c532f16c36a496","settingDisableRenderRequestBody":false,"settingEncodeUrl":true,"settingFollowRedirects":"global","settingRebuildPath":true,"settingSendCookies":true,"settingStoreCookies":true,"url":"{{ base_url  }}/{{ path  }}/5","_type":"request"},{"_id":"fld_a523cf43e0664ea491c532f16c36a496","created":1580844763631,"description":"","environment":{"path":"references"},"environmentPropertyOrder":{"&":["path"]},"metaSortKey":-1580587152299.75,"modified":1580844771401,"name":"Refences","parentId":"wrk_5f81078700b94aa38694c038ace28c54","_type":"request_group"},{"_id":"req_baceaf47b34744acaac52f5847072c2f","authentication":{},"body":{"mimeType":"application/json","text":"{\n\t\"title\": \"Referencia editada\"\n}"},"created":1580844763639,"description":"","headers":[{"id":"pair_ad5ee60f014b4dc6af8bd80b4f65d012","name":"Content-Type","value":"application/json"}],"isPrivate":false,"metaSortKey":-1580739844572,"method":"PUT","modified":1580845165660,"name":"update","parameters":[],"parentId":"fld_a523cf43e0664ea491c532f16c36a496","settingDisableRenderRequestBody":false,"settingEncodeUrl":true,"settingFollowRedirects":"global","settingRebuildPath":true,"settingSendCookies":true,"settingStoreCookies":true,"url":"{{ base_url  }}/{{ path  }}/5","_type":"request"},{"_id":"req_1881e0de38214c209b4180ec34c91af5","authentication":{},"body":{},"created":1580844763638,"description":"","headers":[],"isPrivate":false,"metaSortKey":-1580739456664,"method":"GET","modified":1580844763638,"name":"index","parameters":[],"parentId":"fld_a523cf43e0664ea491c532f16c36a496","settingDisableRenderRequestBody":false,"settingEncodeUrl":true,"settingFollowRedirects":"global","settingRebuildPath":true,"settingSendCookies":true,"settingStoreCookies":true,"url":"{{ base_url  }}/{{ path  }}","_type":"request"},{"_id":"req_cebdd752a2ce4c3e935aee071348a323","authentication":{},"body":{"mimeType":"application/json","text":"{\n\t\"title\": \"Referencia 1\",\n\t\"description\": \"Refe desc\"\n}"},"created":1580844763634,"description":"","headers":[{"id":"pair_3ac76a6cfe584728a1ed8d7a880d6d26","name":"Content-Type","value":"application/json"}],"isPrivate":false,"metaSortKey":-1580737649831,"method":"POST","modified":1580845058734,"name":"store","parameters":[],"parentId":"fld_a523cf43e0664ea491c532f16c36a496","settingDisableRenderRequestBody":false,"settingEncodeUrl":true,"settingFollowRedirects":"global","settingRebuildPath":true,"settingSendCookies":true,"settingStoreCookies":true,"url":"{{ base_url  }}/{{ path  }}","_type":"request"},{"_id":"req_4cf91172a57b4fe68408455c254d885a","authentication":{},"body":{},"created":1580849377289,"description":"","headers":[],"isPrivate":false,"metaSortKey":-1580849377289,"method":"GET","modified":1580849389501,"name":"show","parameters":[],"parentId":"fld_63ebcdb6a6e045cbb79d0e3e47d33702","settingDisableRenderRequestBody":false,"settingEncodeUrl":true,"settingFollowRedirects":"global","settingRebuildPath":true,"settingSendCookies":true,"settingStoreCookies":true,"url":"{{ base_url  }}/{{ path  }}/2","_type":"request"},{"_id":"fld_63ebcdb6a6e045cbb79d0e3e47d33702","created":1580845501354,"description":"","environment":{"path":"topics"},"environmentPropertyOrder":{"&":["path"]},"metaSortKey":-1580511909422.625,"modified":1580845508190,"name":"Topics","parentId":"wrk_5f81078700b94aa38694c038ace28c54","_type":"request_group"},{"_id":"req_6c5496d2ea4f437da64da1d8f24e34dd","authentication":{},"body":{},"created":1580845501391,"description":"","headers":[],"isPrivate":false,"metaSortKey":-1580740859062,"method":"DELETE","modified":1580845687482,"name":"delete","parameters":[],"parentId":"fld_63ebcdb6a6e045cbb79d0e3e47d33702","settingDisableRenderRequestBody":false,"settingEncodeUrl":true,"settingFollowRedirects":"global","settingRebuildPath":true,"settingSendCookies":true,"settingStoreCookies":true,"url":"{{ base_url  }}/{{ path  }}/1","_type":"request"},{"_id":"req_570360477d71442b88e77a3a7094a37f","authentication":{},"body":{"mimeType":"application/json","text":"{\n\t\"title_en\": \"Title in en\"\n}"},"created":1580845501387,"description":"","headers":[{"id":"pair_ad5ee60f014b4dc6af8bd80b4f65d012","name":"Content-Type","value":"application/json"}],"isPrivate":false,"metaSortKey":-1580739844572,"method":"PUT","modified":1580845681035,"name":"update","parameters":[],"parentId":"fld_63ebcdb6a6e045cbb79d0e3e47d33702","settingDisableRenderRequestBody":false,"settingEncodeUrl":true,"settingFollowRedirects":"global","settingRebuildPath":true,"settingSendCookies":true,"settingStoreCookies":true,"url":"{{ base_url  }}/{{ path  }}/1","_type":"request"},{"_id":"req_927b74b8401f4c3c8efd3c62a8c1f540","authentication":{},"body":{},"created":1580845501377,"description":"","headers":[],"isPrivate":false,"metaSortKey":-1580739456664,"method":"GET","modified":1580845501377,"name":"index","parameters":[],"parentId":"fld_63ebcdb6a6e045cbb79d0e3e47d33702","settingDisableRenderRequestBody":false,"settingEncodeUrl":true,"settingFollowRedirects":"global","settingRebuildPath":true,"settingSendCookies":true,"settingStoreCookies":true,"url":"{{ base_url  }}/{{ path  }}","_type":"request"},{"_id":"req_d30689a861b34d86878b60c711bea606","authentication":{},"body":{"mimeType":"application/json","text":"{\n\t\"title_br\": \"Titulo em portugues\",\n\t\"title_en\": \"Titudo em en\",\n\t\"description_br\": \"Descrição em pt\",\n\t\"description_en\": \"Descrição em en\",\n\t\"introduction_br\": \"Introducao em pt\",\n\t\"introduction_en\": \"Introducao em en\"\n}"},"created":1580845501366,"description":"","headers":[{"id":"pair_3ac76a6cfe584728a1ed8d7a880d6d26","name":"Content-Type","value":"application/json"}],"isPrivate":false,"metaSortKey":-1580737649831,"method":"POST","modified":1580845875431,"name":"store","parameters":[],"parentId":"fld_63ebcdb6a6e045cbb79d0e3e47d33702","settingDisableRenderRequestBody":false,"settingEncodeUrl":true,"settingFollowRedirects":"global","settingRebuildPath":true,"settingSendCookies":true,"settingStoreCookies":true,"url":"{{ base_url  }}/{{ path  }}","_type":"request"},{"_id":"req_c1635bb4a6ee49d89ba5b8f666b209f6","authentication":{},"body":{"mimeType":"multipart/form-data","params":[{"description":"","id":"pair_b5b8901576f34819992a31edcdf64111","name":"description","value":"Imgem 2"},{"description":"","id":"pair_d46ff58bd0d849b88fa52f1af64b561c","name":"reference","value":"referencia 2"},{"description":"","disabled":true,"id":"pair_5fd43b9cd10d4ec68393d09f167542f9","name":"","value":""},{"description":"","disabled":false,"fileName":"/Users/manogel/Documents/MODELAGEM BD.png","id":"pair_53b5a027f81f4a3daf5a34c6f1ac2ed9","name":"file","type":"file","value":""}]},"created":1580848086627,"description":"","headers":[{"id":"pair_3ac76a6cfe584728a1ed8d7a880d6d26","name":"Content-Type","value":"multipart/form-data"}],"isPrivate":false,"metaSortKey":-1580740859112,"method":"PUT","modified":1580848927713,"name":"update","parameters":[],"parentId":"fld_a81a926414cc484eab41b590379c4c87","settingDisableRenderRequestBody":false,"settingEncodeUrl":true,"settingFollowRedirects":"global","settingRebuildPath":true,"settingSendCookies":true,"settingStoreCookies":true,"url":"{{ base_url  }}/{{ path  }}/2","_type":"request"},{"_id":"fld_a81a926414cc484eab41b590379c4c87","created":1580846948757,"description":"","environment":{"path":"files"},"environmentPropertyOrder":{"&":["path"]},"metaSortKey":-1580474287984.0625,"modified":1580846956184,"name":"Files","parentId":"wrk_5f81078700b94aa38694c038ace28c54","_type":"request_group"},{"_id":"req_657c4eff87e341c4851d96b73468f9aa","authentication":{},"body":{},"created":1580846948793,"description":"","headers":[],"isPrivate":false,"metaSortKey":-1580740859062,"method":"DELETE","modified":1580849050912,"name":"delete","parameters":[],"parentId":"fld_a81a926414cc484eab41b590379c4c87","settingDisableRenderRequestBody":false,"settingEncodeUrl":true,"settingFollowRedirects":"global","settingRebuildPath":true,"settingSendCookies":true,"settingStoreCookies":true,"url":"{{ base_url  }}/{{ path  }}/2","_type":"request"},{"_id":"req_d7166ef8c3ec4a6bbaa59531f1577736","authentication":{},"body":{},"created":1580846948779,"description":"","headers":[],"isPrivate":false,"metaSortKey":-1580739456664,"method":"GET","modified":1580847004685,"name":"index","parameters":[],"parentId":"fld_a81a926414cc484eab41b590379c4c87","settingDisableRenderRequestBody":false,"settingEncodeUrl":true,"settingFollowRedirects":"global","settingRebuildPath":true,"settingSendCookies":true,"settingStoreCookies":true,"url":"{{ base_url  }}/{{ path  }}","_type":"request"},{"_id":"req_d55bd03d07264da7a13490ecf5e5fb8f","authentication":{},"body":{"mimeType":"multipart/form-data","params":[{"description":"","id":"pair_b5b8901576f34819992a31edcdf64111","name":"description","value":"Imgem 1"},{"description":"","id":"pair_d46ff58bd0d849b88fa52f1af64b561c","name":"reference","value":"referencia 1"},{"description":"","id":"pair_5fd43b9cd10d4ec68393d09f167542f9","name":"topic_id","value":"2"},{"description":"","fileName":"/Users/manogel/Documents/hcl_icone.png","id":"pair_53b5a027f81f4a3daf5a34c6f1ac2ed9","name":"file","type":"file","value":""}]},"created":1580846948768,"description":"","headers":[{"id":"pair_3ac76a6cfe584728a1ed8d7a880d6d26","name":"Content-Type","value":"multipart/form-data"}],"isPrivate":false,"metaSortKey":-1580737649831,"method":"POST","modified":1580847365229,"name":"store","parameters":[],"parentId":"fld_a81a926414cc484eab41b590379c4c87","settingDisableRenderRequestBody":false,"settingEncodeUrl":true,"settingFollowRedirects":"global","settingRebuildPath":true,"settingSendCookies":true,"settingStoreCookies":true,"url":"{{ base_url  }}/{{ path  }}","_type":"request"},{"_id":"req_e55ba1ea17d24a9a9ca3877f6125c47f","authentication":{},"body":{},"created":1580741626821,"description":"","headers":[],"isPrivate":false,"metaSortKey":-1580740859062,"method":"DELETE","modified":1580742302058,"name":"delete","parameters":[],"parentId":"fld_cfd8533ded294edfac10a07993377584","settingDisableRenderRequestBody":false,"settingEncodeUrl":true,"settingFollowRedirects":"global","settingRebuildPath":true,"settingSendCookies":true,"settingStoreCookies":true,"url":"{{ base_url  }}/{{ path  }}/4","_type":"request"},{"_id":"fld_cfd8533ded294edfac10a07993377584","created":1580741626811,"description":"","environment":{"path":"users"},"environmentPropertyOrder":{"&":["path"]},"metaSortKey":-1580436666545.5,"modified":1580741637753,"name":"Users","parentId":"wrk_5f81078700b94aa38694c038ace28c54","_type":"request_group"},{"_id":"req_e0a99c3f4d4a4a86a7c464b60d17afbe","authentication":{},"body":{},"created":1580741626817,"description":"","headers":[],"isPrivate":false,"metaSortKey":-1580739456664,"method":"GET","modified":1580741626817,"name":"index","parameters":[],"parentId":"fld_cfd8533ded294edfac10a07993377584","settingDisableRenderRequestBody":false,"settingEncodeUrl":true,"settingFollowRedirects":"global","settingRebuildPath":true,"settingSendCookies":true,"settingStoreCookies":true,"url":"{{ base_url  }}/{{ path  }}","_type":"request"},{"_id":"req_ce9267a7be65443a867c38113ac8813c","authentication":{},"body":{"mimeType":"application/json","text":"{\n\t\"name\": \"manoel gomes\",\n\t\"birt_date\": \"30/10/1999\",\n\t\"sex\": true\n}"},"created":1580741626815,"description":"","headers":[{"id":"pair_3ac76a6cfe584728a1ed8d7a880d6d26","name":"Content-Type","value":"application/json"}],"isPrivate":false,"metaSortKey":-1580737649831,"method":"POST","modified":1580844296337,"name":"store","parameters":[],"parentId":"fld_cfd8533ded294edfac10a07993377584","settingDisableRenderRequestBody":false,"settingEncodeUrl":true,"settingFollowRedirects":"global","settingRebuildPath":true,"settingSendCookies":true,"settingStoreCookies":true,"url":"{{ base_url  }}/{{ path  }}","_type":"request"},{"_id":"env_f3b4bb2cc4a65cde8b91aabe12e08f9a98363203","color":null,"created":1580737513620,"data":{},"dataPropertyOrder":null,"isPrivate":false,"metaSortKey":1580737513620,"modified":1580737513620,"name":"Base Environment","parentId":"wrk_5f81078700b94aa38694c038ace28c54","_type":"environment"},{"_id":"jar_f3b4bb2cc4a65cde8b91aabe12e08f9a98363203","cookies":[],"created":1580737513626,"modified":1580737513626,"name":"Default Jar","parentId":"wrk_5f81078700b94aa38694c038ace28c54","_type":"cookie_jar"},{"_id":"env_780528e2eb8c409a875b6ea2ccfbde95","color":"#0837f0","created":1580737517935,"data":{"base_url":"http://localhost:3333","token":"eyJhbGciOiJIUzI1NiIsInR5cCI6IkpXVCJ9.eyJ1aWQiOjEsImlhdCI6MTU4MDg0NDI3MX0.HyNRObzMJdmYBqw038ag64jbSow4LrjM8HR1AQfZZ50"},"dataPropertyOrder":{"&":["base_url","token"]},"isPrivate":false,"metaSortKey":1580737517935,"modified":1580844282875,"name":"development","parentId":"env_f3b4bb2cc4a65cde8b91aabe12e08f9a98363203","_type":"environment"},{"_id":"env_ab484dc2b36f4f00bdf8c0a340c13f04","color":"#00b925","created":1580737559702,"data":{"base_url":"http://localhost:3333","token":""},"dataPropertyOrder":{"&":["base_url","token"]},"isPrivate":false,"metaSortKey":1580737559702,"modified":1580737605973,"name":"Production","parentId":"env_f3b4bb2cc4a65cde8b91aabe12e08f9a98363203","_type":"environment"}]}